sensirion_i2c_sht4x/__init__.py
sensirion_i2c_sht4x/commands.py
sensirion_i2c_sht4x/device.py
sensirion_i2c_sht4x/response_provider.py
sensirion_i2c_sht4x/result_types.py
sensirion_i2c_sht4x/version.py
sensirion_i2c_sht4x-1.1.0.dist-info/LICENSE
sensirion_i2c_sht4x-1.1.0.dist-info/METADATA
sensirion_i2c_sht4x-1.1.0.dist-info/WHEEL
sensirion_i2c_sht4x-1.1.0.dist-info/top_level.txt
sensirion_i2c_sht4x-1.1.0.dist-info/RECORD
