Metadata-Version: 2.1
Name: sensirion_i2c_sht4x
Version: 1.1.0
Summary: I2C driver for the Sensirion SHT4X sensor family
Home-page: UNKNOWN
Author: Sensirion
Author-email: info@sensirion.com
License: BSD
Project-URL: Documentation, https://sensirion.github.io/python-i2c-sht4x
Project-URL: Repository, https://github.com/Sensirion/python-i2c-sht4x
Project-URL: Changelog, https://github.com/Sensirion/python-i2c-sht4x/blob/master/CHANGELOG.md
Keywords: Sensirion SHT4X
Platform: UNKNOWN
Classifier: Intended Audience :: Developers
Classifier: License :: OSI Approved :: BSD License
Classifier: Programming Language :: Python :: 3.6
Classifier: Programming Language :: Python :: 3.8
Classifier: Programming Language :: Python :: 3.11
Classifier: Topic :: Software Development :: Libraries :: Python Modules
Requires-Python: >=3.6, <4
Provides-Extra: test
